trtyolo_export/cli.py
trtyolo_export/head.py
trtyolo_export/ppyoloe.py
trtyolo_export-1.0.0.dist-info/licenses/LICENSE
trtyolo_export-1.0.0.dist-info/METADATA
trtyolo_export-1.0.0.dist-info/WHEEL
trtyolo_export-1.0.0.dist-info/entry_points.txt
trtyolo_export-1.0.0.dist-info/top_level.txt
trtyolo_export-1.0.0.dist-info/RECORD
