Metadata-Version: 2.4
Name: trtyolo-export
Version: 1.0.0
Summary: 🛠️ TensorRT-YOLO official exporter: one-click ONNX export for TensorRT-YOLO
Author-email: laugh12321 <laugh12321@vip.qq.com>
Maintainer: laugh12321
License:                     GNU GENERAL PUBLIC LICENSE
Project-URL: Bug Reports, https://github.com/laugh12321/TensorRT-YOLO/issues
Project-URL: Funding, https://github.com/laugh12321
Project-URL: Source, https://github.com/laugh12321/TensorRT-YOLO/tree/trtyolo-export
Keywords: ML,DL,AI,YOLO,YOLOv3,YOLOv5,YOLOv6,YOLOv7,YOLOv8,YOLOv9,YOLOv10,YOLO11,YOLO12,YOLO-World,YOLOE,PP-YOLOE,TensorRT,CUDA,ONNX,computer-vision,image-classification,object-detection,pose-estimation,instance-segmentation,rotated-object-detection,ultralytics
Classifier: Development Status :: 5 - Production/Stable
Classifier: Environment :: Console
Classifier: Intended Audience :: Developers
Classifier: Intended Audience :: Education
Classifier: Intended Audience :: Science/Research
Classifier: License :: OSI Approved :: GNU General Public License v3 (GPLv3)
Classifier: Natural Language :: Chinese (Simplified)
Classifier: Natural Language :: English
Classifier: Operating System :: Microsoft :: Windows
Classifier: Operating System :: POSIX :: Linux
Classifier: Programming Language :: Python :: 3
Classifier: Programming Language :: Python :: 3 :: Only
Classifier: Programming Language :: Python :: 3.8
Classifier: Programming Language :: Python :: 3.9
Classifier: Programming Language :: Python :: 3.10
Classifier: Programming Language :: Python :: 3.11
Classifier: Programming Language :: Python :: 3.12
Classifier: Programming Language :: Python :: 3.13
Classifier: Programming Language :: Python :: 3.14
Classifier: Topic :: Software Development
Classifier: Topic :: Scientific/Engineering
Classifier: Topic :: Scientific/Engineering :: Artificial Intelligence
Classifier: Topic :: Scientific/Engineering :: Image Recognition
Requires-Python: >=3.8
License-File: LICENSE
Requires-Dist: loguru
Requires-Dist: rich_click
Requires-Dist: numpy
Requires-Dist: onnxsim>=0.4.1
Requires-Dist: onnxruntime>=1.6.0
Requires-Dist: onnx_graphsurgeon
Requires-Dist: onnx>=1.12.0
Requires-Dist: ultralytics
Dynamic: license-file
